aptwe/__init__.py
aptwe/exceptions.py
aptwe/functions.py
aptwe/parser.py
aptwe/primitives.py
aptwe/addons/__init__.py
aptwe/addons/char_parsers.py
aptwe/addons/num_parsers.py
examples/__init__.py
examples/json.py
tests/__init__.py
tests/test_compositions.py
tests/test_primitives.py
aptwe-0.1.1.dist-info/LICENSE
aptwe-0.1.1.dist-info/METADATA
aptwe-0.1.1.dist-info/WHEEL
aptwe-0.1.1.dist-info/top_level.txt
aptwe-0.1.1.dist-info/RECORD
