Metadata-Version: 2.1
Name: aptwe
Version: 0.1.1
Summary: Parser framework
Home-page: https://github.com/phuelsdunk/aptwe
Author: Philipp Hülsdunk
Author-email: mail@huelsdunk.tech
License: UNKNOWN
Platform: UNKNOWN
Classifier: Programming Language :: Python :: 3
Classifier: License :: OSI Approved :: MIT License
Classifier: Operating System :: OS Independent
Requires-Python: >=3.6
